{
  "ComponentIndexes": {},
  "ControlUniqueGuids": {},
  "ControlUniqueIds": {
    "App": 1,
    "galleryTemplate3": 51,
    "Host": 3,
    "ScrMenu": 4,
    "ScrMenuLabel2": 6,
    "ScrMenuRectangle1_1": 8,
    "ScrMenuRectangle1_2": 7,
    "ScrMenuRectangle1_3": 5,
    "ScrShList": 9,
    "ScrShListBody2": 60,
    "ScrShListGallery3": 50,
    "ScrShListIcon1": 11,
    "ScrShListIcon2": 13,
    "ScrShListIcon3": 18,
    "ScrShListLabel1": 12,
    "ScrShListNextArrow7": 61,
    "ScrShListRectangle2": 10,
    "ScrShListRectangle7": 63,
    "ScrShListSeparator7": 62,
    "ScrShListSubtitle6": 59,
    "ScrShListTextInput1": 14,
    "ScrShListTitle7": 58,
    "ScrStList": 15,
    "ScrStListIcon1": 16,
    "ScrStListRectangle1": 17
  },
  "FunctionParamsInvariantScripts": {},
  "FunctionParamsInvariantScriptsOnInstances": {},
  "HeaderLastSavedDateTimeUTC": "02/13/2024 02:30:47",
  "IsLegacyComponentAllowGlobalScopeCase": false,
  "LocalConnectionIDReferences": {
    "64f71719-4663-4ff4-b92b-0603d2ef770e": "\"/providers/microsoft.powerapps/apis/shared_excelonlinebusiness/connections/384a7ab89fe24d5bb16961562fb35b71\""
  },
  "LocalDatabaseReferencesAsEmpty": false,
  "LocalResourceFileNames": {},
  "LocalResourceRootPaths": {},
  "OrderComponentMetadata": {},
  "OrderComponentTemplate": {},
  "OrderDataSource": {
    "CustomGallerySample": 0,
    "在庫テーブル": 3,
    "出荷テーブル": 2,
    "入荷テーブル": 1
  },
  "OrderGroupControls": {},
  "OrderPcfTemplate": {},
  "OrderTemplate": {},
  "OrderXMLTemplate": {
    "gallery": 3,
    "icon": 2,
    "label": 1,
    "rectangle": 0,
    "text": 4
  },
  "OverridablePropertiesEntry": {
    "App": {},
    "galleryTemplate3": {},
    "Host": {},
    "ScrMenu": {},
    "ScrMenuLabel2": {},
    "ScrMenuRectangle1_1": {},
    "ScrMenuRectangle1_2": {},
    "ScrMenuRectangle1_3": {},
    "ScrShList": {},
    "ScrShListBody2": {},
    "ScrShListGallery3": {},
    "ScrShListIcon1": {},
    "ScrShListIcon2": {},
    "ScrShListIcon3": {},
    "ScrShListLabel1": {},
    "ScrShListNextArrow7": {},
    "ScrShListRectangle2": {},
    "ScrShListRectangle7": {},
    "ScrShListSeparator7": {},
    "ScrShListSubtitle6": {},
    "ScrShListTextInput1": {},
    "ScrShListTitle7": {},
    "ScrStList": {},
    "ScrStListIcon1": {},
    "ScrStListRectangle1": {}
  },
  "PCFDynamicSchemaForIRRetrievalEntry": {},
  "PCFTemplateEntry": {},
  "PublishOrderIndices": {
    "App": 0,
    "galleryTemplate3": 0,
    "Host": 0,
    "ScrMenu": 3,
    "ScrMenuLabel2": 5,
    "ScrMenuRectangle1_1": 7,
    "ScrMenuRectangle1_2": 6,
    "ScrMenuRectangle1_3": 4,
    "ScrShList": 8,
    "ScrShListBody2": 0,
    "ScrShListGallery3": 0,
    "ScrShListIcon1": 10,
    "ScrShListIcon2": 12,
    "ScrShListIcon3": 0,
    "ScrShListLabel1": 11,
    "ScrShListNextArrow7": 0,
    "ScrShListRectangle2": 9,
    "ScrShListRectangle7": 0,
    "ScrShListSeparator7": 0,
    "ScrShListSubtitle6": 0,
    "ScrShListTextInput1": 13,
    "ScrShListTitle7": 0,
    "ScrStList": 14,
    "ScrStListIcon1": 15,
    "ScrStListRectangle1": 16
  },
  "ResourcesJsonIndices": {
    "Image-SampleImage": 0
  },
  "RuleScreenIdWithoutScreen": {},
  "TemplateVersions": {},
  "VolatileProperties": {
    "AnalysisLoadTime": 0.0977515,
    "ControlCount": {
      "icon": 3,
      "label": 2,
      "rectangle": 5,
      "screen": 3,
      "text": 1
    },
    "DeserializationLoadTime": 0.1981681
  },
  "WasLocalDatabaseReferencesEmpty": true
}